{
  "priority": 5,
  "request_log": "16/08 18:01:18.628  DEBUG [2021-08-16 18:01:18] PING!\n16/08 18:01:18.655  DEBUG [2021-08-16 18:01:18] {:host=>\"192.168.11.221\", :port=>3306, :name=>\"d1\"}\n16/08 18:01:18.656  DEBUG [2021-08-16 18:01:18] {:host=>\"192.168.11.222\", :port=>3306, :name=>\"d2\"}\n16/08 18:01:18.656  DEBUG [2021-08-16 18:01:18] {:host=>\"192.168.11.223\", :port=>3306, :name=>\"d3\"}\n16/08 18:01:18.656  DEBUG [2021-08-16 18:01:18] {:host=>\"192.168.11.224\", :port=>3306, :name=>\"d4\"}\n16/08 18:01:18.656  DEBUG [2021-08-16 18:01:18] [\"d4\", \"d3\", \"d2\", \"d1\"]\n16/08 18:01:18.656  ERROR [2021-08-16 18:01:18] DbRwSplitAdapter:69854429920240: Set write connection to \"d1\"\n16/08 18:01:18.656  ERROR [2021-08-16 18:01:18] DbRwSplitAdapter:69854429920240: Added read connection \"d2\"\n16/08 18:01:18.656  ERROR [2021-08-16 18:01:18] DbRwSplitAdapter:69854429920240: Added read connection \"d3\"\n16/08 18:01:18.656  ERROR [2021-08-16 18:01:18] DbRwSplitAdapter:69854429920240: Added read connection \"d4\"\n16/08 18:01:18.656  DEBUG [2021-08-16 18:01:18] DbRwSplitAdapter:69854429920240:reset_write_state: chose read connection 2\n16/08 18:01:18.656  DEBUG [2021-08-16 18:01:18] DbRwSplitAdapter:69854429920240:reset_write_state: chose read connection 1\n16/08 18:01:18.656  DbRwSplitAdapter:ServerStatusMonitor:69854513564060.on_status_change(69854429920240)\n16/08 18:01:18.656  DEBUG [2021-08-16 18:01:18] DbRwSplitAdapter.start (69854429920240, 69854513564060)\n16/08 18:01:18.658  DEBUG [2021-08-16 18:01:18] SQL (0.000167)  SET NAMES 'utf8mb4'\n16/08 18:01:18.658  DEBUG [2021-08-16 18:01:18] SQL (0.000161)  SET SQL_AUTO_IS_NULL=0\n16/08 18:01:18.658  DEBUG [2021-08-16 18:01:18] DbRwSplitAdapter(force_write):columns\n16/08 18:01:18.659  DEBUG [2021-08-16 18:01:18] Asset Columns (0.000942)  SHOW FIELDS FROM assets\n16/08 18:01:18.662  DEBUG [2021-08-16 18:01:18] SQL (0.000203)  SET NAMES 'utf8mb4'\n16/08 18:01:18.662  DEBUG [2021-08-16 18:01:18] SQL (0.000233)  SET SQL_AUTO_IS_NULL=0\n16/08 18:01:18.663  DEBUG [2021-08-16 18:01:18] Asset Load:DbRwSplitAdapter(d2:read):select_all (0.000643)  SELECT * FROM assets WHERE (assets.`id` = 528323238)\n16/08 18:01:18.868  DEBUG [2021-08-16 18:01:18] SQL (0.000200)  SET NAMES 'utf8mb4'\n16/08 18:01:18.869  DEBUG [2021-08-16 18:01:18] SQL (0.000219)  SET SQL_AUTO_IS_NULL=0\n16/08 18:01:18.870  DEBUG [2021-08-16 18:01:18] SQL (0.000136)  SET NAMES 'utf8mb4'\n16/08 18:01:18.870  DEBUG [2021-08-16 18:01:18] SQL (0.000194)  SET SQL_AUTO_IS_NULL=0\n16/08 18:01:18.871  DEBUG [2021-08-16 18:01:18] DbRwSplitAdapter(force_write):columns\n16/08 18:01:18.872  DEBUG [2021-08-16 18:01:18] User Columns (0.000930)  SHOW FIELDS FROM pikicentral_production.users\n16/08 18:01:18.874  DEBUG [2021-08-16 18:01:18] User Load:DbRwSplitAdapter(d2:read):select_all (0.000678)  SELECT * FROM pikicentral_production.users WHERE (pikicentral_production.users.`id` = 41610508)\n16/08 18:01:18.874  DEBUG [2021-08-16 18:01:18] DbRwSplitAdapter(force_write):columns\n16/08 18:01:18.876  DEBUG [2021-08-16 18:01:18] AffiliateSystem Columns (0.001505)  SHOW FIELDS FROM affiliate_systems\n16/08 18:01:18.879  DEBUG [2021-08-16 18:01:18] AffiliateSystem Load:DbRwSplitAdapter(d2:read):select_all (0.001009)  SELECT * FROM affiliate_systems WHERE (affiliate_systems.`id` = 109432)\n16/08 18:01:18.879  DEBUG [2021-08-16 18:01:18] DbRwSplitAdapter(force_write):columns\n16/08 18:01:18.881  DEBUG [2021-08-16 18:01:18] Branding Columns (0.001473)  SHOW FIELDS FROM brandings\n16/08 18:01:18.884  DEBUG [2021-08-16 18:01:18] Branding Load:DbRwSplitAdapter(d2:read):select_all (0.000798)  SELECT * FROM brandings WHERE (brandings.`id` = 11798492)\n16/08 18:01:18.897  DEBUG [2021-08-16 18:01:18] Using corel\n16/08 18:01:19.160  DEBUG [2021-08-16 18:01:19] Ve::Client.new endpoint:50.18.115.90\n16/08 18:01:19.181  DEBUG [2021-08-16 18:01:19] sending message: {\"size\"=>91221, :action=>\"Vector_GenerateTrueview\", :queue=>\"designer_upload\"}\n16/08 18:01:19.192  DEBUG [2021-08-16 18:01:19] sent message\n16/08 18:01:19.192  DEBUG [2021-08-16 18:01:19] receiving message\n16/08 18:10:05.997  DEBUG [2021-08-16 18:10:05] Got header {\"size\"=>\"0\", \"result-code\"=>\"603\", \"result-message\"=>\"Task dropped, waiting in Queue for too long\"}\n16/08 18:10:05.998  DEBUG [2021-08-16 18:10:05] got message\n16/08 18:10:05.998  DEBUG [2021-08-16 18:10:05] Error generating template design: Task dropped, waiting in Queue for too long:603: Template file written to /tmp/test-Vector_GenerateTrueview.1629100879.18181.error.json\n16/08 18:10:05.999  DEBUG [2021-08-16 18:10:05] Error file written",
  "date": "2021-08-16 18:10:06",
  "release": "stable",
  "rails_env": "production",
  "title": "Error converting to raster: Task dropped, waiting in Queue for too long:603",
  "type": "system",
  "request_id": "b2:stable:dec_Manage_DecorationProcessor_VectorQueueProcessor",
  "hostname": "b2"
}